{
 "召唤师铠甲6阶2": "Giáp EM 6-2",
 "魔剑士靴1阶1": "Giày MG 1-1",
 "魔剑士靴2阶1": "Giày MG 2-1",
 "魔剑士靴3阶1": "Giày MG 3-1",
 "魔剑士靴4阶1": "Giày MG 4-1",
 "魔剑士靴5阶1": "Giày MG 5-1",
 "魔剑士靴6阶1": "Giày MG 6-1",
 "圣导师头盔4阶2": "Mũ DK 4-2",
 "魔剑士靴7阶1": "Giày MG 7-1",
 "魔剑士靴8阶1": "Giày MG 8-1",
 "圣导师头盔5阶2": "Mũ DK 5-2",
 "圣导师头盔6阶2": "Mũ DK 6-2",
 "魔剑士武器1阶2": "Vũ Khí MG 1-2",
 "魔剑士武器2阶2": "Vũ Khí MG 2-2",
 "魔剑士武器3阶2": "Vũ Khí MG 3-2",
 "圣导师戒指4阶1": "Nhẫn DK 4-1",
 "魔剑士武器4阶2": "Vũ Khí MG 4-2",
 "圣导师戒指5阶1": "Nhẫn DK 5-1",
 "圣导师戒指6阶1": "Nhẫn DK 6-1",
 "魔剑士武器5阶2": "Vũ Khí MG 5-2",
 "召唤师护手4阶2": "Bao Tay EM 4-2",
 "圣导师戒指7阶1": "Nhẫn DK 7-1",
 "召唤师护手5阶2": "Bao Tay EM 5-2",
 "圣导师戒指8阶1": "Nhẫn DK 8-1",
 "魔剑士武器6阶2": "Vũ Khí MG 6-2",
 "召唤师护手6阶2": "Bao Tay EM 6-2",
 "召唤师护手7阶2": "Bao Tay EM 7-2",
 "召唤师护手8阶2": "Bao Tay EM 8-2",
 "魔剑士武器8阶2": "Vũ Khí MG 8-2",
 "召唤师武器1阶0": "Vũ Khí EM 1-0",
 "召唤师武器2阶0": "Vũ Khí EM 2-0",
 "召唤师武器3阶0": "Vũ Khí EM 3-0",
 "魔剑士戒指1阶1": "Nhẫn MG 1-1",
 "魔剑士戒指2阶1": "Nhẫn MG 2-1",
 "魔剑士戒指3阶1": "Nhẫn MG 3-1",
 "魔剑士戒指4阶1": "Nhẫn MG 4-1",
 "魔剑士戒指5阶1": "Nhẫn MG 5-1",
 "魔剑士戒指6阶1": "Nhẫn MG 6-1",
 "圣导师护手4阶2": "Bao Tay DK 4-2",
 "圣导师铠甲4阶2": "Giáp DK 4-2",
 "魔剑士戒指7阶1": "Nhẫn MG 7-1",
 "圣导师护手5阶2": "Bao Tay DK 5-2",
 "魔剑士戒指8阶1": "Nhẫn MG 8-1",
 "圣导师护手6阶2": "Bao Tay DK 6-2",
 "圣导师铠甲5阶2": "Giáp DK 5-2",
 "圣导师护手7阶2": "Bao Tay DK 7-2",
 "圣导师护手8阶2": "Bao Tay DK 8-2",
 "圣导师铠甲6阶2": "Giáp DK 6-2",
 "魔剑士头盔1阶2": "Mũ MG 1-2",
 "魔剑士头盔2阶2": "Mũ MG 2-2",
 "魔剑士头盔3阶2": "Mũ MG 3-2",
 "魔剑士头盔4阶2": "Mũ MG 4-2",
 "魔剑士头盔5阶2": "Mũ MG 5-2",
 "召唤师靴4阶2": "Giày EM 4-2",
 "召唤师靴5阶2": "Giày EM 5-2",
 "魔剑士头盔6阶2": "Mũ MG 6-2",
 "召唤师靴6阶2": "Giày EM 6-2",
 "召唤师靴7阶2": "Giày EM 7-2",
 "魔剑士头盔7阶2": "Mũ MG 7-2",
 "召唤师靴8阶2": "Giày EM 8-2",
 "魔剑士头盔8阶2": "Mũ MG 8-2",
 "魔剑士护手1阶2": "Bao Tay MG 1-2",
 "召唤师头盔1阶0": "Mũ EM 1-0",
 "魔剑士护手2阶2": "Bao Tay MG 2-2",
 "魔剑士护手3阶2": "Bao Tay MG 3-2",
 "召唤师头盔2阶0": "Mũ EM 2-0",
 "魔剑士护手4阶2": "Bao Tay MG 4-2",
 "魔剑士护手5阶2": "Bao Tay MG 5-2",
 "召唤师头盔3阶0": "Mũ EM 3-0",
 "魔剑士护手6阶2": "Bao Tay MG 6-2",
 "魔剑士护手7阶2": "Bao Tay MG 7-2",
 "召唤师头盔4阶0": "Mũ EM 4-0",
 "魔剑士护手8阶2": "Bao Tay MG 8-2",
 "召唤师头盔5阶0": "Mũ EM 5-0",
 "召唤师头盔6阶0": "Mũ EM 6-0",
 "圣导师武器1阶0": "Vũ Khí DK 1-0",
 "召唤师头盔7阶0": "Mũ EM 7-0",
 "圣导师武器2阶0": "Vũ Khí DK 2-0",
 "召唤师头盔8阶0": "Mũ EM 8-0",
 "圣导师武器3阶0": "Vũ Khí DK 3-0",
 "圣导师靴4阶2": "Giày DK 4-2",
 "圣导师靴5阶2": "Giày DK 5-2",
 "圣导师武器4阶0": "Vũ Khí DK 4-0",
 "圣导师靴6阶2": "Giày DK 6-2",
 "圣导师靴7阶2": "Giày DK 7-2",
 "圣导师武器5阶0": "Vũ Khí DK 5-0",
 "圣导师靴8阶2": "Giày DK 8-2",
 "魔剑士铠甲1阶2": "Giáp MG 1-2",
 "圣导师武器6阶0": "Vũ Khí DK 6-0",
 "魔剑士铠甲2阶2": "Giáp MG 2-2",
 "圣导师武器7阶0": "Vũ Khí DK 7-0",
 "魔剑士铠甲3阶2": "Giáp MG 3-2",
 "圣导师武器8阶0": "Vũ Khí DK 8-0",
 "魔剑士铠甲4阶2": "Giáp MG 4-2",
 "召唤师护腿2阶0": "Quần EM 2-0",
 "魔剑士铠甲5阶2": "Giáp MG 5-2",
 "召唤师戒指4阶2": "Nhẫn EM 4-2",
 "召唤师护腿4阶0": "Quần EM 4-0",
 "召唤师戒指5阶2": "Nhẫn EM 5-2",
 "魔剑士铠甲6阶2": "Giáp MG 6-2",
 "召唤师戒指6阶2": "Nhẫn EM 6-2",
 "召唤师护腿6阶0": "Quần EM 6-0",
 "召唤师戒指7阶2": "Nhẫn EM 7-2",
 "魔剑士铠甲7阶2": "Giáp MG 7-2",
 "召唤师戒指8阶2": "Nhẫn EM 8-2",
 "召唤师护腿8阶0": "Quần EM 8-0",
 "魔剑士铠甲8阶2": "Giáp MG 8-2",
 "魔剑士靴1阶2": "Giày MG 1-2",
 "召唤师铠甲1阶0": "Giáp EM 1-0",
 "魔剑士靴2阶2": "Giày MG 2-2",
 "魔剑士靴3阶2": "Giày MG 3-2",
 "召唤师铠甲2阶0": "Giáp EM 2-0",
 "魔剑士靴4阶2": "Giày MG 4-2",
 "魔剑士靴5阶2": "Giày MG 5-2",
 "召唤师铠甲3阶0": "Giáp EM 3-0",
 "魔剑士靴6阶2": "Giày MG 6-2",
 "魔剑士靴7阶2": "Giày MG 7-2",
 "召唤师铠甲4阶0": "Giáp EM 4-0",
 "魔剑士靴8阶2": "Giày MG 8-2",
 "召唤师铠甲5阶0": "Giáp EM 5-0",
 "召唤师铠甲6阶0": "Giáp EM 6-0",
 "圣导师头盔1阶0": "Mũ DK 1-0",
 "召唤师铠甲7阶0": "Giáp EM 7-0",
 "圣导师头盔2阶0": "Mũ DK 2-0",
 "圣导师护腿1阶0": "Quần DK 1-0",
 "圣导师护腿2阶0": "Quần DK 2-0",
 "召唤师铠甲8阶0": "Giáp EM 8-0",
 "圣导师头盔3阶0": "Mũ DK 3-0",
 "圣导师护腿3阶0": "Quần DK 3-0",
 "圣导师戒指4阶2": "Nhẫn DK 4-2",
 "圣导师护腿4阶0": "Quần DK 4-0",
 "圣导师戒指5阶2": "Nhẫn DK 5-2",
 "圣导师头盔4阶0": "Mũ DK 4-0",
 "圣导师护腿5阶0": "Quần DK 5-0",
 "圣导师戒指6阶2": "Nhẫn DK 6-2",
 "召唤师护手4阶3": "Bao Tay EM 4-3",
 "圣导师护腿6阶0": "Quần DK 6-0",
 "圣导师戒指7阶2": "Nhẫn DK 7-2",
 "圣导师头盔5阶0": "Mũ DK 5-0",
 "召唤师护手5阶3": "Bao Tay EM 5-3",
 "圣导师护腿7阶0": "Quần DK 7-0",
 "圣导师戒指8阶2": "Nhẫn DK 8-2",
 "召唤师护手6阶3": "Bao Tay EM 6-3",
 "圣导师护腿8阶0": "Quần DK 8-0",
 "召唤师武器4阶3": "Vũ Khí EM 4-3",
 "圣导师头盔6阶0": "Mũ DK 6-0",
 "召唤师护手7阶3": "Bao Tay EM 7-3",
 "魔剑士武器1阶0": "Vũ Khí MG 1-0",
 "召唤师护手8阶3": "Bao Tay EM 8-3",
 "召唤师武器5阶3": "Vũ Khí EM 5-3",
 "圣导师头盔7阶0": "Mũ DK 7-0",
 "魔剑士武器2阶0": "Vũ Khí MG 2-0",
 "召唤师武器6阶3": "Vũ Khí EM 6-3",
 "圣导师头盔8阶0": "Mũ DK 8-0",
 "魔剑士武器3阶0": "Vũ Khí MG 3-0",
 "召唤师项链1阶0": "Dây Chuyền EM 1-0",
 "召唤师武器7阶3": "Vũ Khí EM 7-3",
 "召唤师项链2阶0": "Dây Chuyền EM 2-0",
 "魔剑士武器4阶0": "Vũ Khí MG 4-0",
 "召唤师项链3阶0": "Dây Chuyền EM 3-0",
 "召唤师武器8阶3": "Vũ Khí EM 8-3",
 "召唤师项链4阶0": "Dây Chuyền EM 4-0",
 "魔剑士武器5阶0": "Vũ Khí MG 5-0",
 "召唤师项链5阶0": "Dây Chuyền EM 5-0",
 "召唤师项链6阶0": "Dây Chuyền EM 6-0",
 "魔剑士武器6阶0": "Vũ Khí MG 6-0",
 "召唤师项链7阶0": "Dây Chuyền EM 7-0",
 "召唤师项链8阶0": "Dây Chuyền EM 8-0",
 "魔剑士武器7阶0": "Vũ Khí MG 7-0",
 "魔剑士武器8阶0": "Vũ Khí MG 8-0",
 "魔剑士戒指1阶2": "Nhẫn MG 1-2",
 "魔剑士戒指2阶2": "Nhẫn MG 2-2",
 "魔剑士护腿2阶0": "Quần MG 2-0",
 "魔剑士戒指3阶2": "Nhẫn MG 3-2",
 "魔剑士戒指4阶2": "Nhẫn MG 4-2",
 "魔剑士护腿4阶0": "Quần MG 4-0",
 "魔剑士戒指5阶2": "Nhẫn MG 5-2",
 "魔剑士戒指6阶2": "Nhẫn MG 6-2",
 "圣导师护手4阶3": "Bao Tay DK 4-3",
 "魔剑士护腿6阶0": "Quần MG 6-0",
 "魔剑士戒指7阶2": "Nhẫn MG 7-2",
 "圣导师护手5阶3": "Bao Tay DK 5-3",
 "魔剑士戒指8阶2": "Nhẫn MG 8-2",
 "圣导师护手6阶3": "Bao Tay DK 6-3",
 "魔剑士护腿8阶0": "Quần MG 8-0",
 "圣导师护手7阶3": "Bao Tay DK 7-3",
 "圣导师护手8阶3": "Bao Tay DK 8-3",
 "圣导师铠甲1阶0": "Giáp DK 1-0",
 "圣导师铠甲2阶0": "Giáp DK 2-0",
 "圣导师项链1阶0": "Dây Chuyền DK 1-0",
 "圣导师项链2阶0": "Dây Chuyền DK 2-0",
 "圣导师铠甲3阶0": "Giáp DK 3-0",
 "圣导师项链3阶0": "Dây Chuyền DK 3-0",
 "圣导师项链4阶0": "Dây Chuyền DK 4-0",
 "圣导师铠甲4阶0": "Giáp DK 4-0",
 "圣导师项链5阶0": "Dây Chuyền DK 5-0",
 "召唤师靴4阶3": "Giày EM 4-3",
 "圣导师项链6阶0": "Dây Chuyền DK 6-0",
 "圣导师铠甲5阶0": "Giáp DK 5-0",
 "召唤师靴5阶3": "Giày EM 5-3",
 "圣导师项链7阶0": "Dây Chuyền DK 7-0",
 "召唤师靴6阶3": "Giày EM 6-3",
 "圣导师项链8阶0": "Dây Chuyền DK 8-0",
 "召唤师头盔4阶3": "Mũ EM 4-3",
 "圣导师铠甲6阶0": "Giáp DK 6-0",
 "召唤师靴7阶3": "Giày EM 7-3",
 "魔剑士头盔1阶0": "Mũ MG 1-0",
 "召唤师靴8阶3": "Giày EM 8-3",
 "召唤师头盔5阶3": "Mũ EM 5-3",
 "圣导师铠甲7阶0": "Giáp DK 7-0",
 "魔剑士头盔2阶0": "Mũ MG 2-0",
 "召唤师头盔6阶3": "Mũ EM 6-3",
 "圣导师铠甲8阶0": "Giáp DK 8-0",
 "魔剑士头盔3阶0": "Mũ MG 3-0",
 "魔剑士护手1阶3": "Bao Tay MG 1-3",
 "魔剑士护手2阶3": "Bao Tay MG 2-3",
 "魔剑士头盔4阶0": "Mũ MG 4-0",
 "魔剑士护手3阶3": "Bao Tay MG 3-3",
 "魔剑士护手4阶3": "Bao Tay MG 4-3",
 "魔剑士头盔5阶0": "Mũ MG 5-0",
 "魔剑士护手5阶3": "Bao Tay MG 5-3",
 "魔剑士护手6阶3": "Bao Tay MG 6-3",
 "圣导师武器4阶3": "Vũ Khí DK 4-3",
 "魔剑士头盔6阶0": "Mũ MG 6-0",
 "魔剑士护手7阶3": "Bao Tay MG 7-3",
 "魔剑士护手8阶3": "Bao Tay MG 8-3",
 "圣导师武器5阶3": "Vũ Khí DK 5-3",
 "魔剑士头盔7阶0": "Mũ MG 7-0",
 "圣导师武器6阶3": "Vũ Khí DK 6-3",
 "魔剑士头盔8阶0": "Mũ MG 8-0",
 "魔剑士项链1阶0": "Dây Chuyền MG 1-0",
 "圣导师武器7阶3": "Vũ Khí DK 7-3",
 "魔剑士项链2阶0": "Dây Chuyền MG 2-0",
 "魔剑士项链3阶0": "Dây Chuyền MG 3-0",
 "圣导师武器8阶3": "Vũ Khí DK 8-3",
 "魔剑士项链4阶0": "Dây Chuyền MG 4-0",
 "魔剑士项链5阶0": "Dây Chuyền MG 5-0",
 "圣导师靴4阶3": "Giày DK 4-3",
 "魔剑士项链6阶0": "Dây Chuyền MG 6-0",
 "圣导师靴5阶3": "Giày DK 5-3",
 "魔剑士项链7阶0": "Dây Chuyền MG 7-0",
 "圣导师靴6阶3": "Giày DK 6-3",
 "魔剑士项链8阶0": "Dây Chuyền MG 8-0",
 "圣导师靴7阶3": "Giày DK 7-3",
 "圣导师靴8阶3": "Giày DK 8-3",
 "召唤师戒指4阶3": "Nhẫn EM 4-3",
 "召唤师戒指5阶3": "Nhẫn EM 5-3",
 "召唤师护腿5阶1": "Quần EM 5-1",
 "召唤师戒指6阶3": "Nhẫn EM 6-3",
 "召唤师铠甲4阶3": "Giáp EM 4-3",
 "召唤师戒指7阶3": "Nhẫn EM 7-3",
 "魔剑士铠甲1阶0": "Giáp MG 1-0",
 "召唤师护腿7阶1": "Quần EM 7-1",
 "召唤师戒指8阶3": "Nhẫn EM 8-3",
 "召唤师铠甲5阶3": "Giáp EM 5-3",
 "魔剑士铠甲2阶0": "Giáp MG 2-0",
 "召唤师铠甲6阶3": "Giáp EM 6-3",
 "魔剑士铠甲3阶0": "Giáp MG 3-0",
 "魔剑士靴1阶3": "Giày MG 1-3",
 "魔剑士靴2阶3": "Giày MG 2-3",
 "魔剑士铠甲4阶0": "Giáp MG 4-0",
 "魔剑士靴3阶3": "Giày MG 3-3",
 "魔剑士靴4阶3": "Giày MG 4-3",
 "魔剑士铠甲5阶0": "Giáp MG 5-0",
 "魔剑士靴5阶3": "Giày MG 5-3",
 "魔剑士靴6阶3": "Giày MG 6-3",
 "圣导师头盔4阶3": "Mũ DK 4-3",
 "魔剑士铠甲6阶0": "Giáp MG 6-0",
 "魔剑士靴7阶3": "Giày MG 7-3",
 "魔剑士靴8阶3": "Giày MG 8-3",
 "圣导师头盔5阶3": "Mũ DK 5-3",
 "魔剑士铠甲7阶0": "Giáp MG 7-0",
 "圣导师头盔6阶3": "Mũ DK 6-3",
 "魔剑士铠甲8阶0": "Giáp MG 8-0",
 "魔剑士武器1阶3": "Vũ Khí MG 1-3",
 "魔剑士武器2阶3": "Vũ Khí MG 2-3",
 "魔剑士武器3阶3": "Vũ Khí MG 3-3",
 "圣导师戒指4阶3": "Nhẫn DK 4-3",
 "魔剑士武器4阶3": "Vũ Khí MG 4-3",
 "圣导师护腿4阶1": "Quần DK 4-1",
 "圣导师护腿5阶1": "Quần DK 5-1",
 "圣导师戒指6阶3": "Nhẫn DK 6-3",
 "魔剑士武器5阶3": "Vũ Khí MG 5-3",
 "圣导师护腿6阶1": "Quần DK 6-1",
 "圣导师护腿7阶1": "Quần DK 7-1",
 "圣导师戒指8阶3": "Nhẫn DK 8-3",
 "魔剑士武器6阶3": "Vũ Khí MG 6-3",
 "圣导师护腿8阶1": "Quần DK 8-1",
 "魔剑士武器7阶3": "Vũ Khí MG 7-3",
 "魔剑士武器8阶3": "Vũ Khí MG 8-3",
 "召唤师项链4阶1": "Dây Chuyền EM 4-1",
 "召唤师项链5阶1": "Dây Chuyền EM 5-1",
 "召唤师项链6阶1": "Dây Chuyền EM 6-1",
 "召唤师项链7阶1": "Dây Chuyền EM 7-1",
 "召唤师武器4阶1": "Vũ Khí EM 4-1",
 "召唤师项链8阶1": "Dây Chuyền EM 8-1",
 "召唤师武器5阶1": "Vũ Khí EM 5-1",
 "魔剑士戒指1阶3": "Nhẫn MG 1-3",
 "召唤师武器6阶1": "Vũ Khí EM 6-1",
 "魔剑士护腿1阶1": "Quần MG 1-1",
 "魔剑士戒指2阶3": "Nhẫn MG 2-3",
 "魔剑士戒指3阶3": "Nhẫn MG 3-3",
 "召唤师武器7阶1": "Vũ Khí EM 7-1",
 "魔剑士护腿3阶1": "Quần MG 3-1",
 "魔剑士戒指4阶3": "Nhẫn MG 4-3",
 "魔剑士戒指5阶3": "Nhẫn MG 5-3",
 "召唤师武器8阶1": "Vũ Khí EM 8-1",
 "魔剑士护腿5阶1": "Quần MG 5-1",
 "魔剑士戒指6阶3": "Nhẫn MG 6-3",
 "魔剑士护腿6阶1": "Quần MG 6-1",
 "魔剑士戒指7阶3": "Nhẫn MG 7-3",
 "魔剑士护腿7阶1": "Quần MG 7-1",
 "魔剑士戒指8阶3": "Nhẫn MG 8-3",
 "魔剑士护腿8阶1": "Quần MG 8-1",
 "圣导师铠甲6阶3": "Giáp DK 6-3",
 "魔剑士头盔1阶3": "Mũ MG 1-3",
 "魔剑士头盔2阶3": "Mũ MG 2-3",
 "魔剑士头盔3阶3": "Mũ MG 3-3",
 "魔剑士头盔4阶3": "Mũ MG 4-3",
 "圣导师项链4阶1": "Dây Chuyền DK 4-1",
 "圣导师项链5阶1": "Dây Chuyền DK 5-1",
 "魔剑士头盔5阶3": "Mũ MG 5-3",
 "圣导师项链6阶1": "Dây Chuyền DK 6-1",
 "圣导师项链7阶1": "Dây Chuyền DK 7-1",
 "魔剑士头盔6阶3": "Mũ MG 6-3",
 "圣导师项链8阶1": "Dây Chuyền DK 8-1",
 "魔剑士头盔7阶3": "Mũ MG 7-3",
 "魔剑士头盔8阶3": "Mũ MG 8-3",
 "召唤师头盔4阶1": "Mũ EM 4-1",
 "召唤师头盔5阶1": "Mũ EM 5-1",
 "召唤师头盔6阶1": "Mũ EM 6-1",
 "魔剑士项链1阶1": "Dây Chuyền MG 1-1",
 "魔剑士项链2阶1": "Dây Chuyền MG 2-1",
 "召唤师头盔7阶1": "Mũ EM 7-1",
 "魔剑士项链3阶1": "Dây Chuyền MG 3-1",
 "魔剑士项链4阶1": "Dây Chuyền MG 4-1",
 "召唤师头盔8阶1": "Mũ EM 8-1",
 "魔剑士项链5阶1": "Dây Chuyền MG 5-1",
 "魔剑士项链6阶1": "Dây Chuyền MG 6-1",
 "魔剑士项链7阶1": "Dây Chuyền MG 7-1",
 "圣导师武器4阶1": "Vũ Khí DK 4-1",
 "魔剑士项链8阶1": "Dây Chuyền MG 8-1",
 "圣导师武器5阶1": "Vũ Khí DK 5-1",
 "魔剑士铠甲1阶3": "Giáp MG 1-3",
 "圣导师武器6阶1": "Vũ Khí DK 6-1",
 "圣导师武器7阶1": "Vũ Khí DK 7-1",
 "圣导师武器8阶1": "Vũ Khí DK 8-1",
 "召唤师护腿4阶2": "Quần EM 4-2",
 "魔剑士铠甲6阶3": "Giáp MG 6-3",
 "召唤师护腿6阶2": "Quần EM 6-2",
 "魔剑士铠甲7阶3": "Giáp MG 7-3",
 "召唤师护腿8阶2": "Quần EM 8-2",
 "魔剑士铠甲8阶3": "Giáp MG 8-3",
 "召唤师铠甲4阶1": "Giáp EM 4-1",
 "召唤师铠甲5阶1": "Giáp EM 5-1",
 "召唤师铠甲6阶1": "Giáp EM 6-1",
 "召唤师铠甲7阶1": "Giáp EM 7-1",
 "召唤师铠甲8阶1": "Giáp EM 8-1",
 "圣导师护腿4阶2": "Quần DK 4-2",
 "圣导师护腿5阶2": "Quần DK 5-2",
 "圣导师护腿6阶2": "Quần DK 6-2",
 "圣导师护腿7阶2": "Quần DK 7-2",
 "圣导师护腿8阶2": "Quần DK 8-2",
 "圣导师头盔6阶1": "Mũ DK 6-1",
 "魔剑士武器1阶1": "Vũ Khí MG 1-1",
 "圣导师头盔7阶1": "Mũ DK 7-1",
 "魔剑士武器2阶1": "Vũ Khí MG 2-1",
 "圣导师头盔8阶1": "Mũ DK 8-1",
 "魔剑士武器3阶1": "Vũ Khí MG 3-1",
 "召唤师护手1阶0": "Bao Tay EM 1-0",
 "魔剑士武器4阶1": "Vũ Khí MG 4-1",
 "召唤师护手2阶0": "Bao Tay EM 2-0",
 "召唤师护手3阶0": "Bao Tay EM 3-0",
 "召唤师项链4阶2": "Dây Chuyền EM 4-2",
 "魔剑士武器5阶1": "Vũ Khí MG 5-1",
 "召唤师护手4阶0": "Bao Tay EM 4-0",
 "召唤师项链5阶2": "Dây Chuyền EM 5-2",
 "召唤师项链6阶2": "Dây Chuyền EM 6-2",
 "魔剑士武器6阶1": "Vũ Khí MG 6-1",
 "召唤师护手6阶0": "Bao Tay EM 6-0",
 "召唤师项链7阶2": "Dây Chuyền EM 7-2",
 "召唤师项链8阶2": "Dây Chuyền EM 8-2",
 "魔剑士武器7阶1": "Vũ Khí MG 7-1",
 "召唤师护手8阶0": "Bao Tay EM 8-0",
 "魔剑士武器8阶1": "Vũ Khí MG 8-1",
 "魔剑士护腿2阶2": "Quần MG 2-2",
 "魔剑士护腿4阶2": "Quần MG 4-2",
 "魔剑士护腿6阶2": "Quần MG 6-2",
 "魔剑士护腿8阶2": "Quần MG 8-2",
 "圣导师护手1阶0": "Bao Tay DK 1-0",
 "圣导师护手2阶0": "Bao Tay DK 2-0",
 "圣导师护手3阶0": "Bao Tay DK 3-0",
 "圣导师项链4阶2": "Dây Chuyền DK 4-2",
 "圣导师护手4阶0": "Bao Tay DK 4-0",
 "圣导师铠甲4阶1": "Giáp DK 4-1",
 "圣导师项链5阶2": "Dây Chuyền DK 5-2",
 "圣导师护手5阶0": "Bao Tay DK 5-0",
 "圣导师项链6阶2": "Dây Chuyền DK 6-2",
 "圣导师护手6阶0": "Bao Tay DK 6-0",
 "圣导师铠甲5阶1": "Giáp DK 5-1",
 "圣导师项链7阶2": "Dây Chuyền DK 7-2",
 "圣导师护手7阶0": "Bao Tay DK 7-0",
 "圣导师项链8阶2": "Dây Chuyền DK 8-2",
 "圣导师护手8阶0": "Bao Tay DK 8-0",
 "圣导师铠甲6阶1": "Giáp DK 6-1",
 "魔剑士头盔1阶1": "Mũ MG 1-1",
 "圣导师铠甲7阶1": "Giáp DK 7-1",
 "魔剑士头盔2阶1": "Mũ MG 2-1",
 "圣导师铠甲8阶1": "Giáp DK 8-1",
 "魔剑士头盔3阶1": "Mũ MG 3-1",
 "召唤师靴1阶0": "Giày EM 1-0",
 "召唤师靴2阶0": "Giày EM 2-0",
 "召唤师靴3阶0": "Giày EM 3-0",
 "召唤师靴4阶0": "Giày EM 4-0",
 "召唤师靴5阶0": "Giày EM 5-0",
 "魔剑士头盔6阶1": "Mũ MG 6-1",
 "召唤师靴6阶0": "Giày EM 6-0",
 "召唤师靴7阶0": "Giày EM 7-0",
 "魔剑士头盔7阶1": "Mũ MG 7-1",
 "召唤师靴8阶0": "Giày EM 8-0",
 "魔剑士头盔8阶1": "Mũ MG 8-1",
 "魔剑士项链1阶2": "Dây Chuyền MG 1-2",
 "魔剑士护手1阶0": "Bao Tay MG 1-0",
 "魔剑士项链2阶2": "Dây Chuyền MG 2-2",
 "魔剑士护手2阶0": "Bao Tay MG 2-0",
 "魔剑士项链3阶2": "Dây Chuyền MG 3-2",
 "魔剑士护手3阶0": "Bao Tay MG 3-0",
 "魔剑士项链4阶2": "Dây Chuyền MG 4-2",
 "魔剑士护手4阶0": "Bao Tay MG 4-0",
 "魔剑士项链5阶2": "Dây Chuyền MG 5-2",
 "魔剑士项链6阶2": "Dây Chuyền MG 6-2",
 "魔剑士护手6阶0": "Bao Tay MG 6-0",
 "魔剑士项链7阶2": "Dây Chuyền MG 7-2",
 "魔剑士项链8阶2": "Dây Chuyền MG 8-2",
 "魔剑士护手8阶0": "Bao Tay MG 8-0",
 "圣导师靴1阶0": "Giày DK 1-0",
 "圣导师靴2阶0": "Giày DK 2-0",
 "圣导师戒指2阶1": "Nhẫn DK 2-1",
 "圣导师靴3阶0": "Giày DK 3-0",
 "圣导师靴4阶0": "Giày DK 4-0",
 "圣导师靴5阶0": "Giày DK 5-0",
 "圣导师靴6阶0": "Giày DK 6-0",
 "召唤师护腿5阶3": "Quần EM 5-3",
 "圣导师靴7阶0": "Giày DK 7-0",
 "召唤师护腿6阶3": "Quần EM 6-3",
 "圣导师靴8阶0": "Giày DK 8-0",
 "魔剑士铠甲1阶1": "Giáp MG 1-1",
 "召唤师护腿7阶3": "Quần EM 7-3",
 "召唤师护腿8阶3": "Quần EM 8-3",
 "魔剑士铠甲2阶1": "Giáp MG 2-1",
 "魔剑士铠甲3阶1": "Giáp MG 3-1",
 "召唤师戒指1阶0": "Nhẫn EM 1-0",
 "魔剑士铠甲4阶1": "Giáp MG 4-1",
 "召唤师戒指2阶0": "Nhẫn EM 2-0",
 "召唤师戒指3阶0": "Nhẫn EM 3-0",
 "魔剑士铠甲5阶1": "Giáp MG 5-1",
 "召唤师戒指4阶0": "Nhẫn EM 4-0",
 "召唤师戒指5阶0": "Nhẫn EM 5-0",
 "魔剑士铠甲6阶1": "Giáp MG 6-1",
 "召唤师戒指6阶0": "Nhẫn EM 6-0",
 "召唤师戒指7阶0": "Nhẫn EM 7-0",
 "魔剑士铠甲7阶1": "Giáp MG 7-1",
 "召唤师戒指8阶0": "Nhẫn EM 8-0",
 "魔剑士铠甲8阶1": "Giáp MG 8-1",
 "魔剑士靴1阶0": "Giày MG 1-0",
 "魔剑士靴2阶0": "Giày MG 2-0",
 "魔剑士靴3阶0": "Giày MG 3-0",
 "魔剑士靴4阶0": "Giày MG 4-0",
 "魔剑士靴5阶0": "Giày MG 5-0",
 "圣导师护腿4阶3": "Quần DK 4-3",
 "魔剑士靴6阶0": "Giày MG 6-0",
 "圣导师护腿5阶3": "Quần DK 5-3",
 "魔剑士靴7阶0": "Giày MG 7-0",
 "圣导师护腿6阶3": "Quần DK 6-3",
 "魔剑士靴8阶0": "Giày MG 8-0",
 "圣导师护腿7阶3": "Quần DK 7-3",
 "魔剑士铠甲4阶3": "Giáp MG 4-3",
 "圣导师戒指1阶2": "Nhẫn DK 1-2",
 "圣导师护腿8阶3": "Quần DK 8-3",
 "召唤师护腿6阶1": "Quần EM 6-1",
 "圣导师戒指1阶0": "Nhẫn DK 1-0",
 "圣导师戒指2阶0": "Nhẫn DK 2-0",
 "圣导师戒指3阶0": "Nhẫn DK 3-0",
 "圣导师戒指4阶0": "Nhẫn DK 4-0",
 "圣导师戒指5阶0": "Nhẫn DK 5-0",
 "召唤师项链4阶3": "Dây Chuyền EM 4-3",
 "圣导师戒指6阶0": "Nhẫn DK 6-0",
 "召唤师项链5阶3": "Dây Chuyền EM 5-3",
 "圣导师戒指7阶0": "Nhẫn DK 7-0",
 "召唤师护手5阶1": "Bao Tay EM 5-1",
 "召唤师项链6阶3": "Dây Chuyền EM 6-3",
 "圣导师戒指8阶0": "Nhẫn DK 8-0",
 "召唤师项链7阶3": "Dây Chuyền EM 7-3",
 "召唤师武器4阶2": "Vũ Khí EM 4-2",
 "召唤师护手7阶1": "Bao Tay EM 7-1",
 "召唤师项链8阶3": "Dây Chuyền EM 8-3",
 "召唤师武器5阶2": "Vũ Khí EM 5-2",
 "召唤师武器6阶2": "Vũ Khí EM 6-2",
 "魔剑士护腿1阶3": "Quần MG 1-3",
 "召唤师武器7阶2": "Vũ Khí EM 7-2",
 "魔剑士护腿3阶3": "Quần MG 3-3",
 "召唤师武器8阶2": "Vũ Khí EM 8-2",
 "魔剑士护腿5阶3": "Quần MG 5-3",
 "召唤师靴2阶2": "Giày EM 2-2",
 "召唤师靴3阶3": "Giày EM 3-3",
 "召唤师项链2阶2": "Dây Chuyền EM 2-2",
 "魔剑士护腿6阶3": "Quần MG 6-3",
 "召唤师项链3阶2": "Dây Chuyền EM 3-2",
 "召唤师戒指1阶2": "Nhẫn EM 1-2",
 "魔剑士护腿7阶3": "Quần MG 7-3",
 "魔剑士护腿8阶3": "Quần MG 8-3",
 "召唤师武器2阶3": "Vũ Khí EM 2-3",
 "魔剑士戒指1阶0": "Nhẫn MG 1-0",
 "魔剑士戒指2阶0": "Nhẫn MG 2-0",
 "魔剑士戒指3阶0": "Nhẫn MG 3-0",
 "圣导师护手1阶1": "Bao Tay DK 1-1",
 "魔剑士戒指4阶0": "Nhẫn MG 4-0",
 "圣导师护手2阶1": "Bao Tay DK 2-1",
 "魔剑士戒指5阶0": "Nhẫn MG 5-0",
 "圣导师护手3阶1": "Bao Tay DK 3-1",
 "圣导师项链4阶3": "Dây Chuyền DK 4-3",
 "魔剑士戒指6阶0": "Nhẫn MG 6-0",
 "圣导师护手4阶1": "Bao Tay DK 4-1",
 "魔剑士头盔4阶1": "Mũ MG 4-1",
 "圣导师项链5阶3": "Dây Chuyền DK 5-3",
 "魔剑士戒指7阶0": "Nhẫn MG 7-0",
 "魔剑士护手5阶0": "Bao Tay MG 5-0",
 "圣导师护手5阶1": "Bao Tay DK 5-1",
 "圣导师项链6阶3": "Dây Chuyền DK 6-3",
 "魔剑士戒指8阶0": "Nhẫn MG 8-0",
 "圣导师护手6阶1": "Bao Tay DK 6-1",
 "圣导师项链7阶3": "Dây Chuyền DK 7-3",
 "圣导师护手7阶1": "Bao Tay DK 7-1",
 "圣导师项链8阶3": "Dây Chuyền DK 8-3",
 "圣导师护手8阶1": "Bao Tay DK 8-1",
 "圣导师护腿2阶2": "Quần DK 2-2",
 "圣导师铠甲1阶2": "Giáp DK 1-2",
 "召唤师护手8阶1": "Bao Tay EM 8-1",
 "召唤师铠甲3阶3": "Giáp EM 3-3",
 "魔剑士护腿4阶3": "Quần MG 4-3",
 "召唤师头盔1阶3": "Mũ EM 1-3",
 "魔剑士武器7阶2": "Vũ Khí MG 7-2",
 "圣导师戒指5阶3": "Nhẫn DK 5-3",
 "魔剑士铠甲2阶3": "Giáp MG 2-3",
 "召唤师靴4阶1": "Giày EM 4-1",
 "魔剑士护腿1阶0": "Quần MG 1-0",
 "魔剑士护腿3阶0": "Quần MG 3-0",
 "召唤师戒指3阶3": "Nhẫn EM 3-3",
 "召唤师戒指3阶2": "Nhẫn EM 3-2",
 "召唤师戒指3阶1": "Nhẫn EM 3-1",
 "召唤师靴5阶1": "Giày EM 5-1",
 "召唤师戒指2阶3": "Nhẫn EM 2-3",
 "召唤师戒指2阶2": "Nhẫn EM 2-2",
 "召唤师戒指2阶1": "Nhẫn EM 2-1",
 "召唤师戒指1阶3": "Nhẫn EM 1-3",
 "召唤师戒指1阶1": "Nhẫn EM 1-1",
 "召唤师靴6阶1": "Giày EM 6-1",
 "召唤师项链3阶3": "Dây Chuyền EM 3-3",
 "召唤师项链3阶1": "Dây Chuyền EM 3-1",
 "召唤师项链2阶3": "Dây Chuyền EM 2-3",
 "召唤师头盔4阶2": "Mũ EM 4-2",
 "召唤师项链2阶1": "Dây Chuyền EM 2-1",
 "召唤师靴7阶1": "Giày EM 7-1",
 "召唤师项链1阶3": "Dây Chuyền EM 1-3",
 "召唤师项链1阶2": "Dây Chuyền EM 1-2",
 "召唤师项链1阶1": "Dây Chuyền EM 1-1",
 "召唤师靴3阶1": "Giày EM 3-1",
 "召唤师靴3阶2": "Giày EM 3-2",
 "召唤师靴8阶1": "Giày EM 8-1",
 "召唤师靴2阶3": "Giày EM 2-3",
 "召唤师靴2阶1": "Giày EM 2-1",
 "召唤师靴1阶3": "Giày EM 1-3",
 "召唤师头盔5阶2": "Mũ EM 5-2",
 "召唤师靴1阶2": "Giày EM 1-2",
 "召唤师靴1阶1": "Giày EM 1-1",
 "召唤师护腿8阶1": "Quần EM 8-1",
 "召唤师护腿7阶2": "Quần EM 7-2",
 "召唤师护腿7阶0": "Quần EM 7-0",
 "召唤师护腿5阶2": "Quần EM 5-2",
 "召唤师护腿5阶0": "Quần EM 5-0",
 "召唤师护腿4阶3": "Quần EM 4-3",
 "召唤师护腿4阶1": "Quần EM 4-1",
 "召唤师护腿3阶3": "Quần EM 3-3",
 "召唤师护腿3阶2": "Quần EM 3-2",
 "召唤师头盔6阶2": "Mũ EM 6-2",
 "召唤师护腿3阶1": "Quần EM 3-1",
 "召唤师护腿3阶0": "Quần EM 3-0",
 "魔剑士项链1阶3": "Dây Chuyền MG 1-3",
 "召唤师护腿2阶3": "Quần EM 2-3",
 "召唤师护腿2阶2": "Quần EM 2-2",
 "魔剑士护手1阶1": "Bao Tay MG 1-1",
 "召唤师护腿2阶1": "Quần EM 2-1",
 "召唤师护腿1阶3": "Quần EM 1-3",
 "魔剑士项链2阶3": "Dây Chuyền MG 2-3",
 "召唤师护腿1阶2": "Quần EM 1-2",
 "召唤师护腿1阶1": "Quần EM 1-1",
 "召唤师护腿1阶0": "Quần EM 1-0",
 "魔剑士护手2阶1": "Bao Tay MG 2-1",
 "召唤师护手7阶0": "Bao Tay EM 7-0",
 "魔剑士项链3阶3": "Dây Chuyền MG 3-3",
 "召唤师护手6阶1": "Bao Tay EM 6-1",
 "召唤师护手5阶0": "Bao Tay EM 5-0",
 "魔剑士护手3阶1": "Bao Tay MG 3-1",
 "召唤师护手4阶1": "Bao Tay EM 4-1",
 "召唤师护手3阶3": "Bao Tay EM 3-3",
 "魔剑士项链4阶3": "Dây Chuyền MG 4-3",
 "召唤师护手3阶2": "Bao Tay EM 3-2",
 "召唤师护手3阶1": "Bao Tay EM 3-1",
 "召唤师护手2阶3": "Bao Tay EM 2-3",
 "魔剑士护手4阶1": "Bao Tay MG 4-1",
 "召唤师护手2阶2": "Bao Tay EM 2-2",
 "召唤师护手2阶1": "Bao Tay EM 2-1",
 "魔剑士项链5阶3": "Dây Chuyền MG 5-3",
 "召唤师护手1阶3": "Bao Tay EM 1-3",
 "召唤师护手1阶2": "Bao Tay EM 1-2",
 "魔剑士护手5阶1": "Bao Tay MG 5-1",
 "召唤师护手1阶1": "Bao Tay EM 1-1",
 "召唤师铠甲8阶3": "Giáp EM 8-3",
 "魔剑士项链6阶3": "Dây Chuyền MG 6-3",
 "召唤师铠甲8阶2": "Giáp EM 8-2",
 "召唤师铠甲7阶3": "Giáp EM 7-3",
 "召唤师铠甲7阶2": "Giáp EM 7-2",
 "魔剑士护手6阶1": "Bao Tay MG 6-1",
 "魔剑士项链7阶3": "Dây Chuyền MG 7-3",
 "圣导师武器4阶2": "Vũ Khí DK 4-2",
 "召唤师铠甲3阶2": "Giáp EM 3-2",
 "召唤师铠甲3阶1": "Giáp EM 3-1",
 "魔剑士护手7阶1": "Bao Tay MG 7-1",
 "召唤师铠甲2阶3": "Giáp EM 2-3",
 "召唤师铠甲2阶2": "Giáp EM 2-2",
 "魔剑士项链8阶3": "Dây Chuyền MG 8-3",
 "召唤师铠甲2阶1": "Giáp EM 2-1",
 "召唤师铠甲1阶3": "Giáp EM 1-3",
 "召唤师铠甲1阶2": "Giáp EM 1-2",
 "召唤师铠甲1阶1": "Giáp EM 1-1",
 "魔剑士护手8阶1": "Bao Tay MG 8-1",
 "召唤师头盔8阶3": "Mũ EM 8-3",
 "召唤师头盔8阶2": "Mũ EM 8-2",
 "召唤师头盔7阶3": "Mũ EM 7-3",
 "召唤师头盔7阶2": "Mũ EM 7-2",
 "圣导师武器5阶2": "Vũ Khí DK 5-2",
 "召唤师头盔3阶3": "Mũ EM 3-3",
 "召唤师头盔3阶2": "Mũ EM 3-2",
 "召唤师头盔3阶1": "Mũ EM 3-1",
 "召唤师头盔2阶3": "Mũ EM 2-3",
 "召唤师头盔2阶2": "Mũ EM 2-2",
 "召唤师头盔2阶1": "Mũ EM 2-1",
 "召唤师头盔1阶2": "Mũ EM 1-2",
 "召唤师头盔1阶1": "Mũ EM 1-1",
 "召唤师武器8阶0": "Vũ Khí EM 8-0",
 "召唤师武器7阶0": "Vũ Khí EM 7-0",
 "召唤师武器6阶0": "Vũ Khí EM 6-0",
 "召唤师武器5阶0": "Vũ Khí EM 5-0",
 "圣导师武器6阶2": "Vũ Khí DK 6-2",
 "召唤师武器4阶0": "Vũ Khí EM 4-0",
 "召唤师武器3阶3": "Vũ Khí EM 3-3",
 "召唤师武器3阶2": "Vũ Khí EM 3-2",
 "召唤师武器3阶1": "Vũ Khí EM 3-1",
 "召唤师武器2阶2": "Vũ Khí EM 2-2",
 "召唤师武器2阶1": "Vũ Khí EM 2-1",
 "召唤师武器1阶3": "Vũ Khí EM 1-3",
 "召唤师武器1阶2": "Vũ Khí EM 1-2",
 "召唤师武器1阶1": "Vũ Khí EM 1-1",
 "圣导师戒指7阶3": "Nhẫn DK 7-3",
 "圣导师武器7阶2": "Vũ Khí DK 7-2",
 "圣导师戒指3阶3": "Nhẫn DK 3-3",
 "圣导师戒指3阶2": "Nhẫn DK 3-2",
 "圣导师戒指3阶1": "Nhẫn DK 3-1",
 "圣导师戒指2阶3": "Nhẫn DK 2-3",
 "圣导师戒指2阶2": "Nhẫn DK 2-2",
 "圣导师戒指1阶3": "Nhẫn DK 1-3",
 "圣导师戒指1阶1": "Nhẫn DK 1-1",
 "圣导师项链3阶3": "Dây Chuyền DK 3-3",
 "圣导师武器8阶2": "Vũ Khí DK 8-2",
 "圣导师项链3阶2": "Dây Chuyền DK 3-2",
 "圣导师项链3阶1": "Dây Chuyền DK 3-1",
 "圣导师项链2阶3": "Dây Chuyền DK 2-3",
 "圣导师项链2阶2": "Dây Chuyền DK 2-2",
 "圣导师项链2阶1": "Dây Chuyền DK 2-1",
 "圣导师项链1阶3": "Dây Chuyền DK 1-3",
 "圣导师项链1阶2": "Dây Chuyền DK 1-2",
 "圣导师项链1阶1": "Dây Chuyền DK 1-1",
 "圣导师铠甲4阶3": "Giáp DK 4-3",
 "圣导师护手1阶3": "Bao Tay DK 1-3",
 "圣导师护腿2阶1": "Quần DK 2-1",
 "圣导师靴1阶2": "Giày DK 1-2",
 "圣导师靴3阶3": "Giày DK 3-3",
 "圣导师靴4阶1": "Giày DK 4-1",
 "圣导师靴3阶2": "Giày DK 3-2",
 "圣导师靴3阶1": "Giày DK 3-1",
 "圣导师靴2阶3": "Giày DK 2-3",
 "圣导师靴2阶2": "Giày DK 2-2",
 "圣导师靴2阶1": "Giày DK 2-1",
 "圣导师靴1阶3": "Giày DK 1-3",
 "圣导师靴5阶1": "Giày DK 5-1",
 "圣导师靴1阶1": "Giày DK 1-1",
 "圣导师护腿3阶3": "Quần DK 3-3",
 "圣导师护腿3阶2": "Quần DK 3-2",
 "圣导师护腿3阶1": "Quần DK 3-1",
 "圣导师护腿2阶3": "Quần DK 2-3",
 "圣导师靴6阶1": "Giày DK 6-1",
 "圣导师护腿1阶3": "Quần DK 1-3",
 "圣导师护腿1阶2": "Quần DK 1-2",
 "圣导师护腿1阶1": "Quần DK 1-1",
 "圣导师护手3阶3": "Bao Tay DK 3-3",
 "圣导师护手3阶2": "Bao Tay DK 3-2",
 "圣导师护手2阶3": "Bao Tay DK 2-3",
 "圣导师护手2阶2": "Bao Tay DK 2-2",
 "圣导师靴7阶1": "Giày DK 7-1",
 "圣导师护手1阶2": "Bao Tay DK 1-2",
 "圣导师铠甲8阶3": "Giáp DK 8-3",
 "圣导师铠甲8阶2": "Giáp DK 8-2",
 "圣导师铠甲7阶3": "Giáp DK 7-3",
 "圣导师铠甲7阶2": "Giáp DK 7-2",
 "圣导师铠甲5阶3": "Giáp DK 5-3",
 "圣导师靴8阶1": "Giày DK 8-1",
 "圣导师铠甲3阶3": "Giáp DK 3-3",
 "圣导师铠甲3阶2": "Giáp DK 3-2",
 "圣导师铠甲3阶1": "Giáp DK 3-1",
 "圣导师铠甲2阶3": "Giáp DK 2-3",
 "圣导师铠甲2阶2": "Giáp DK 2-2",
 "圣导师铠甲2阶1": "Giáp DK 2-1",
 "圣导师铠甲1阶3": "Giáp DK 1-3",
 "圣导师铠甲1阶1": "Giáp DK 1-1",
 "圣导师头盔8阶3": "Mũ DK 8-3",
 "圣导师头盔8阶2": "Mũ DK 8-2",
 "圣导师头盔7阶3": "Mũ DK 7-3",
 "圣导师头盔7阶2": "Mũ DK 7-2",
 "圣导师头盔5阶1": "Mũ DK 5-1",
 "圣导师头盔4阶1": "Mũ DK 4-1",
 "圣导师头盔3阶3": "Mũ DK 3-3",
 "圣导师头盔3阶2": "Mũ DK 3-2",
 "圣导师头盔3阶1": "Mũ DK 3-1",
 "圣导师头盔2阶3": "Mũ DK 2-3",
 "圣导师头盔2阶2": "Mũ DK 2-2",
 "圣导师头盔2阶1": "Mũ DK 2-1",
 "圣导师头盔1阶3": "Mũ DK 1-3",
 "圣导师头盔1阶2": "Mũ DK 1-2",
 "圣导师头盔1阶1": "Mũ DK 1-1",
 "圣导师武器3阶3": "Vũ Khí DK 3-3",
 "圣导师武器3阶2": "Vũ Khí DK 3-2",
 "圣导师武器3阶1": "Vũ Khí DK 3-1",
 "圣导师武器2阶3": "Vũ Khí DK 2-3",
 "圣导师武器2阶2": "Vũ Khí DK 2-2",
 "圣导师武器2阶1": "Vũ Khí DK 2-1",
 "圣导师武器1阶3": "Vũ Khí DK 1-3",
 "圣导师武器1阶2": "Vũ Khí DK 1-2",
 "圣导师武器1阶1": "Vũ Khí DK 1-1",
 "魔剑士护腿7阶2": "Quần MG 7-2",
 "魔剑士护腿7阶0": "Quần MG 7-0",
 "魔剑士护腿5阶2": "Quần MG 5-2",
 "魔剑士护腿5阶0": "Quần MG 5-0",
 "魔剑士护腿4阶1": "Quần MG 4-1",
 "魔剑士护腿3阶2": "Quần MG 3-2",
 "召唤师戒指4阶1": "Nhẫn EM 4-1",
 "魔剑士护腿2阶3": "Quần MG 2-3",
 "魔剑士护腿2阶1": "Quần MG 2-1",
 "魔剑士护腿1阶2": "Quần MG 1-2",
 "召唤师戒指5阶1": "Nhẫn EM 5-1",
 "魔剑士护手7阶0": "Bao Tay MG 7-0",
 "魔剑士铠甲5阶3": "Giáp MG 5-3",
 "魔剑士铠甲3阶3": "Giáp MG 3-3",
 "召唤师戒指6阶1": "Nhẫn EM 6-1",
 "魔剑士头盔5阶1": "Mũ MG 5-1",
 "召唤师铠甲4阶2": "Giáp EM 4-2",
 "召唤师戒指7阶1": "Nhẫn EM 7-1",
 "召唤师戒指8阶1": "Nhẫn EM 8-1",
 "召唤师铠甲5阶2": "Giáp EM 5-2"
}